anago/__init__.py
anago/callbacks.py
anago/layers.py
anago/models.py
anago/preprocessing.py
anago/tagger.py
anago/trainer.py
anago/utils.py
anago/wrapper.py
anago-1.0.8.dist-info/DESCRIPTION.rst
anago-1.0.8.dist-info/METADATA
anago-1.0.8.dist-info/RECORD
anago-1.0.8.dist-info/WHEEL
anago-1.0.8.dist-info/metadata.json
anago-1.0.8.dist-info/top_level.txt
