Metadata-Version: 2.0
Name: anago
Version: 1.0.8
Summary: Sequence labeling library using Keras.
Home-page: https://github.com/Hironsan/anago
Author: Hironsan
Author-email: hiroki.nakayama.py@gmail.com
License: MIT
Platform: UNKNOWN
Classifier: License :: OSI Approved :: MIT License
Classifier: Programming Language :: Python
Classifier: Programming Language :: Python :: 2.6
Classifier: Programming Language :: Python :: 2.7
Classifier: Programming Language :: Python :: 3
Classifier: Programming Language :: Python :: 3.3
Classifier: Programming Language :: Python :: 3.4
Classifier: Programming Language :: Python :: 3.5
Classifier: Programming Language :: Python :: 3.6
Classifier: Programming Language :: Python :: Implementation :: CPython
Classifier: Programming Language :: Python :: Implementation :: PyPy
Requires-Dist: Keras (>=2.2.0)
Requires-Dist: h5py (>=2.7.1)
Requires-Dist: scikit-learn (>=0.19.1)
Requires-Dist: numpy (>=1.14.3)
Requires-Dist: tensorflow (>=1.8.0)
Requires-Dist: requests (>=2.18.4)
Requires-Dist: seqeval (>=0.0.3)
